powerfox/__init__.py
powerfox/exceptions.py
powerfox/models.py
powerfox/powerfox.py
powerfox/py.typed
powerfox-2.0.0.dist-info/METADATA
powerfox-2.0.0.dist-info/WHEEL
powerfox-2.0.0.dist-info/licenses/LICENSE
powerfox-2.0.0.dist-info/RECORD
