Metadata-Version: 2.4
Name: powerfox
Version: 2.0.0
Summary: Asynchronous Python client for the Powerfox devices
License-Expression: MIT
License-File: LICENSE
Keywords: powerfox,energy,poweropti,api,async,client
Author: Klaas Schoute
Author-email: <hello@student-techlife.com>
Maintainer: Klaas Schoute
Maintainer-email: <hello@student-techlife.com>
Requires-Python: >=3.12
Classifier: Framework :: AsyncIO
Classifier: Intended Audience :: Developers
Classifier: License :: OSI Approved :: MIT License
Classifier: Natural Language :: English
Classifier: Programming Language :: Python :: 3.12
Classifier: Programming Language :: Python :: 3.13
Classifier: Programming Language :: Python :: 3.14
Classifier: Programming Language :: Python :: 3
Classifier: Topic :: Software Development :: Libraries :: Python Modules
Requires-Dist: aiohttp (>=3.0.0)
Requires-Dist: mashumaro (>=3.12,<4.0)
Requires-Dist: orjson (>=3.9.13,<4.0.0)
Requires-Dist: yarl (>=1.6.0)
Project-URL: Bug Tracker, https://github.com/klaasnicolaas/python-powerfox/issues
Project-URL: Changelog, https://github.com/klaasnicolaas/python-powerfox/releases
Project-URL: Documentation, https://github.com/klaasnicolaas/python-powerfox
Project-URL: Homepage, https://github.com/klaasnicolaas/python-powerfox
Project-URL: Repository, https://github.com/klaasnicolaas/python-powerfox
